tntorch/__init__.py
tntorch/anova.py
tntorch/autodiff.py
tntorch/automata.py
tntorch/create.py
tntorch/cross.py
tntorch/derivatives.py
tntorch/interpolation.py
tntorch/logic.py
tntorch/matrix.py
tntorch/maxvol.py
tntorch/metrics.py
tntorch/ops.py
tntorch/round.py
tntorch/tensor.py
tntorch/tools.py
tntorch-1.1.2.dist-info/LICENSE
tntorch-1.1.2.dist-info/METADATA
tntorch-1.1.2.dist-info/WHEEL
tntorch-1.1.2.dist-info/top_level.txt
tntorch-1.1.2.dist-info/RECORD
